Metadata-Version: 2.1
Name: form2tk
Version: 0.1.4
Summary: a code extension used for creating form or matrix in tkinter.
Home-page: https://github.com/rumba-lun/form2tk
Author: @Rumba_lun
Author-email: 342753080@qq.com
License: MIT
Platform: UNKNOWN
Classifier: License :: OSI Approved :: MIT License
Classifier: Programming Language :: Python
Classifier: Programming Language :: Python :: 3
Classifier: Programming Language :: Python :: 3.6
Classifier: Programming Language :: Python :: Implementation :: CPython
Classifier: Programming Language :: Python :: Implementation :: PyPy
Requires-Python: >=3.6.0
License-File: LICENSE
